just_bench_it/__init__.py
just_bench_it/benchmarker.py
just_bench_it/cnn_example.py
just_bench_it/envs.py
just_bench_it/rand_example.py
just_bench_it/utils.py
just_bench_it-0.1.9.dist-info/METADATA
just_bench_it-0.1.9.dist-info/WHEEL
just_bench_it-0.1.9.dist-info/top_level.txt
just_bench_it-0.1.9.dist-info/RECORD
