Metadata-Version: 2.1
Name: just-bench-it
Version: 0.1.9
Summary: A simple benchmarking tool for RL algorithms on Atari games
Home-page: https://github.com/justbechit/just_bench_it
Author: stone91
Author-email: 370025263@qq.com
License: UNKNOWN
Platform: UNKNOWN
Requires-Dist: autorom[accept-rom-license]
Requires-Dist: psutil
Requires-Dist: dill
Requires-Dist: tqdm
Requires-Dist: colorama
Requires-Dist: gymnasium[atari]
Requires-Dist: numpy (<2.0.0)
Requires-Dist: torch
Requires-Dist: requests
